McUtils/__init__.py
McUtils/Combinatorics/Permutations.py
McUtils/Combinatorics/Sequences.py
McUtils/Combinatorics/YoungTableaux.py
McUtils/Combinatorics/__init__.py
McUtils/Coordinerds/Conveniences.py
McUtils/Coordinerds/Conversions.py
McUtils/Coordinerds/Generators.py
McUtils/Coordinerds/Internals.py
McUtils/Coordinerds/Labels.py
McUtils/Coordinerds/Pruning.py
McUtils/Coordinerds/Redundant.py
McUtils/Coordinerds/ZMatrices.py
McUtils/Coordinerds/__init__.py
McUtils/Coordinerds/CoordinateSystems/CartesianToSpherical.py
McUtils/Coordinerds/CoordinateSystems/CartesianToZMatrix.py
McUtils/Coordinerds/CoordinateSystems/CartesianToZMatrix_opt.py
McUtils/Coordinerds/CoordinateSystems/CommonCoordinateSystems.py
McUtils/Coordinerds/CoordinateSystems/CompositeCoordinateSystems.py
McUtils/Coordinerds/CoordinateSystems/CoordinateSet.py
McUtils/Coordinerds/CoordinateSystems/CoordinateSystem.py
McUtils/Coordinerds/CoordinateSystems/CoordinateSystemConverter.py
McUtils/Coordinerds/CoordinateSystems/CoordinateUtils.py
McUtils/Coordinerds/CoordinateSystems/DefaultConverters.py
McUtils/Coordinerds/CoordinateSystems/GenericInternalCoordinateSystem.py
McUtils/Coordinerds/CoordinateSystems/IterativeZMatrixCoordinateSystem.py
McUtils/Coordinerds/CoordinateSystems/SphericalToCartesian.py
McUtils/Coordinerds/CoordinateSystems/ZMatrixToCartesian.py
McUtils/Coordinerds/CoordinateSystems/__init__.py
McUtils/Data/AtomData.py
McUtils/Data/BondData.py
McUtils/Data/ColorData.py
McUtils/Data/CommonData.py
McUtils/Data/ConstantsData.py
McUtils/Data/PotentialData.py
McUtils/Data/QuantityArray.py
McUtils/Data/WavefunctionData.py
McUtils/Data/__init__.py
McUtils/Data/TheRealMcCoy/AtomData.py
McUtils/Data/TheRealMcCoy/BondData.py
McUtils/Data/TheRealMcCoy/ColorData.py
McUtils/Data/TheRealMcCoy/ConstantsData.py
McUtils/Data/TheRealMcCoy/PotentialData.py
McUtils/Data/TheRealMcCoy/WavefunctionData.py
McUtils/Data/TheRealMcCoy/__init__.py
McUtils/Devutils/FileHelpers.py
McUtils/Devutils/Loggers.py
mccoygroup_mcutils-1.6.0.2.dist-info/licenses/LICENSE.txt
mccoygroup_mcutils-1.6.0.2.dist-info/METADATA
mccoygroup_mcutils-1.6.0.2.dist-info/WHEEL
mccoygroup_mcutils-1.6.0.2.dist-info/top_level.txt
mccoygroup_mcutils-1.6.0.2.dist-info/RECORD
