Metadata-Version: 2.4
Name: mccoygroup-mcutils
Version: 1.6.0.2
Author: Mark Boyer
Author-email: maboyer@tamu.edu
License: MIT
License-File: LICENSE.txt
Requires-Dist: numpy>=1.8
Requires-Dist: scipy>=1.7.0
Requires-Dist: h5py>=2.10.0
Requires-Dist: numba>=0.57.1
Requires-Dist: matplotlib>=3.3.4
Dynamic: author
Dynamic: author-email
Dynamic: description
Dynamic: description-content-type
Dynamic: license
Dynamic: license-file
Dynamic: requires-dist
